{"cameraMode":{"drawMode":0,"name":"Shaded","section":"Shading Mode"},"sceneLighting":false,"audioPlay":false,"sceneViewState":{"showFog":true,"showMaterialUpdate":false,"showSkybox":true,"showFlares":true,"showImageEffects":true,"showParticleSystems":true,"showVisualEffectGraphs":true,"m_FxEnabled":true},"in2DMode":false,"pivot":{"x":74.86648559570313,"y":-0.43605780601501467,"z":50.05719757080078},"rotation":{"x":-0.14464561641216279,"y":-0.7025731801986694,"z":0.14930009841918946,"w":-0.6806054711341858},"size":3.9339425563812258,"orthographic":false}